sec_edgar/__init__.py
sec_edgar/financial_statements/__init__.py
sec_edgar/financial_statements/financial_statements.py
sec_edgar/utils/__init__.py
sec_edgar/utils/data_log.py
sec_edgar-0.0.2.data/data/LICENSE.txt
sec_edgar-0.0.2.data/data/MANIFEST.in
sec_edgar-0.0.2.data/data/README.md
sec_edgar-0.0.2.data/data/requirements.txt
sec_edgar-0.0.2.dist-info/LICENSE.txt
sec_edgar-0.0.2.dist-info/METADATA
sec_edgar-0.0.2.dist-info/WHEEL
sec_edgar-0.0.2.dist-info/top_level.txt
sec_edgar-0.0.2.dist-info/RECORD
