Metadata-Version: 2.1
Name: sec-edgar
Version: 0.0.2
Summary: A package for automatically downloading & updating data from the SEC Edgar database
Home-page: https://github.com/davidsilva2841/sec_project
Author: David Silva
Author-email: david.silva2841+python@gmail.com
License: UNKNOWN
Platform: UNKNOWN
Classifier: Programming Language :: Python :: 3
Classifier: License :: OSI Approved :: MIT License
Classifier: Operating System :: OS Independent
Classifier: Topic :: Office/Business :: Financial :: Investment
